fonsolemenu/__init__.py
fonsolemenu/fonsolemenu.py
fonsolemenu/fonsoleoption.py
fonsolemenu-0.1.0.dist-info/LICENSE
fonsolemenu-0.1.0.dist-info/METADATA
fonsolemenu-0.1.0.dist-info/WHEEL
fonsolemenu-0.1.0.dist-info/top_level.txt
fonsolemenu-0.1.0.dist-info/RECORD
