Metadata-Version: 2.1
Name: fonsolemenu
Version: 0.1.0
Summary: Simple console menu for windows
Home-page: https://github.com/Fadix47/fonsolemenu
Author: Fadix Meier
Author-email: fadix18123@gmail.com
Project-URL: Bug Tracker, https://github.com/Fadix47/fonsolemenu/issues
Classifier: Programming Language :: Python :: 3
Classifier: License :: OSI Approved :: MIT License
Classifier: Operating System :: OS Independent
Requires-Python: >=3.7
License-File: LICENSE
